[{"line":1,"elements":[{"start_timestamp":"2025-03-21T06:59:48.975Z","line":4,"name":"serach item in goggle","description":"","id":"feature-to-search-on-to-goggle;serach-item-in-goggle","type":"scenario","keyword":"Scenario","steps":[{"result":{"duration":4184201300,"status":"passed"},"line":5,"name":"user is on goggle page","match":{"location":"com.test.demotest.user_is_on_goggle_page()"},"keyword":"Given "},{"result":{"duration":75841500,"status":"passed"},"line":6,"name":"user enters item name in search textfeild","match":{"location":"com.test.demotest.user_enters_item_name_in_textfeild()"},"keyword":"When "},{"result":{"duration":191340900,"status":"passed"},"line":7,"name":"user clicks on search button","match":{"location":"com.test.demotest.user_clicks_on_search_button()"},"keyword":"And "},{"result":{"duration":1634394000,"status":"passed"},"line":8,"name":"products details should display","match":{"location":"com.test.demotest.products_details_should_display()"},"keyword":"Then "}],"tags":[{"name":"@smoketest"}]}],"name":"feature to search on to Goggle","description":"","id":"feature-to-search-on-to-goggle","keyword":"Feature","uri":"file:src/test/resources/Features/login.feature","tags":[]},{"line":1,"elements":[{"start_timestamp":"2025-03-21T06:59:55.082Z","line":13,"name":"user should be logged in successfully","description":"","id":"feature-to-login-with-valid-credentials;user-should-be-logged-in-successfully;;2","type":"scenario","keyword":"Scenario Outline","steps":[{"result":{"duration":1963623400,"status":"passed"},"line":5,"name":"user is on saucedemo page","match":{"location":"com.test.loginDDT.user_is_on_saucedemo_page()"},"keyword":"Given "},{"result":{"duration":157373400,"status":"passed"},"line":6,"name":"user enters the standard_user and secret_sauce","match":{"arguments":[{"val":"standard_user","offset":16},{"val":"secret_sauce","offset":34}],"location":"com.test.loginDDT.user_enters_the_username_and_password(java.lang.String,java.lang.String)"},"keyword":"When "},{"result":{"duration":98000400,"status":"passed"},"line":7,"name":"user clicks on login  button","match":{"location":"com.test.loginDDT.user_clicks_on_login_button()"},"keyword":"And "},{"result":{"status":"passed"},"line":8,"name":"user should Navigate to homepage","match":{"location":"com.test.loginDDT.user_should_navigate_to_homepage()"},"keyword":"Then "}],"tags":[{"name":"@smoketest"}]},{"start_timestamp":"2025-03-21T06:59:57.307Z","line":14,"name":"user should be logged in successfully","description":"","id":"feature-to-login-with-valid-credentials;user-should-be-logged-in-successfully;;3","type":"scenario","keyword":"Scenario Outline","steps":[{"result":{"duration":2023679900,"status":"passed"},"line":5,"name":"user is on saucedemo page","match":{"location":"com.test.loginDDT.user_is_on_saucedemo_page()"},"keyword":"Given "},{"result":{"duration":146997400,"status":"passed"},"line":6,"name":"user enters the locked_out_user and secret_sauce","match":{"arguments":[{"val":"locked_out_user","offset":16},{"val":"secret_sauce","offset":36}],"location":"com.test.loginDDT.user_enters_the_username_and_password(java.lang.String,java.lang.String)"},"keyword":"When "},{"result":{"duration":76999600,"status":"passed"},"line":7,"name":"user clicks on login  button","match":{"location":"com.test.loginDDT.user_clicks_on_login_button()"},"keyword":"And "},{"result":{"status":"passed"},"line":8,"name":"user should Navigate to homepage","match":{"location":"com.test.loginDDT.user_should_navigate_to_homepage()"},"keyword":"Then "}],"tags":[{"name":"@smoketest"}]},{"start_timestamp":"2025-03-21T06:59:59.558Z","line":15,"name":"user should be logged in successfully","description":"","id":"feature-to-login-with-valid-credentials;user-should-be-logged-in-successfully;;4","type":"scenario","keyword":"Scenario Outline","steps":[{"result":{"duration":1972780800,"status":"passed"},"line":5,"name":"user is on saucedemo page","match":{"location":"com.test.loginDDT.user_is_on_saucedemo_page()"},"keyword":"Given "},{"result":{"duration":146000400,"status":"passed"},"line":6,"name":"user enters the problem_user and secret_sauce","match":{"arguments":[{"val":"problem_user","offset":16},{"val":"secret_sauce","offset":33}],"location":"com.test.loginDDT.user_enters_the_username_and_password(java.lang.String,java.lang.String)"},"keyword":"When "},{"result":{"duration":107000000,"status":"passed"},"line":7,"name":"user clicks on login  button","match":{"location":"com.test.loginDDT.user_clicks_on_login_button()"},"keyword":"And "},{"result":{"duration":999800,"status":"passed"},"line":8,"name":"user should Navigate to homepage","match":{"location":"com.test.loginDDT.user_should_navigate_to_homepage()"},"keyword":"Then "}],"tags":[{"name":"@smoketest"}]},{"start_timestamp":"2025-03-21T07:00:01.790Z","line":16,"name":"user should be logged in successfully","description":"","id":"feature-to-login-with-valid-credentials;user-should-be-logged-in-successfully;;5","type":"scenario","keyword":"Scenario Outline","steps":[{"result":{"duration":2042041400,"status":"passed"},"line":5,"name":"user is on saucedemo page","match":{"location":"com.test.loginDDT.user_is_on_saucedemo_page()"},"keyword":"Given "},{"result":{"duration":185001400,"status":"passed"},"line":6,"name":"user enters the performance_glitch_user and secret_sauce","match":{"arguments":[{"val":"performance_glitch_user","offset":16},{"val":"secret_sauce","offset":44}],"location":"com.test.loginDDT.user_enters_the_username_and_password(java.lang.String,java.lang.String)"},"keyword":"When "},{"result":{"duration":5109994900,"status":"passed"},"line":7,"name":"user clicks on login  button","match":{"location":"com.test.loginDDT.user_clicks_on_login_button()"},"keyword":"And "},{"result":{"status":"passed"},"line":8,"name":"user should Navigate to homepage","match":{"location":"com.test.loginDDT.user_should_navigate_to_homepage()"},"keyword":"Then "}],"tags":[{"name":"@smoketest"}]}],"name":"feature to login with valid credentials","description":"","id":"feature-to-login-with-valid-credentials","keyword":"Feature","uri":"file:src/test/resources/Features/userDDTlogin.feature","tags":[]}]